README.md
setup.py
command_reminder/__init__.py
command_reminder/common.py
command_reminder/exceptions.py
command_reminder.egg-info/PKG-INFO
command_reminder.egg-info/SOURCES.txt
command_reminder.egg-info/dependency_links.txt
command_reminder.egg-info/requires.txt
command_reminder.egg-info/top_level.txt
command_reminder/cli/__init__.py
command_reminder/cli/initializer.py
command_reminder/cli/parser.py
command_reminder/cli/processors.py
command_reminder/config/__init__.py
command_reminder/config/config.py
command_reminder/config/peristent_repository_config.py
command_reminder/operations/__init__.py
command_reminder/operations/base_processors.py
command_reminder/operations/init_repository.py
command_reminder/operations/list_commands.py
command_reminder/operations/list_tags.py
command_reminder/operations/load_command.py
command_reminder/operations/pull_external_repo.py
command_reminder/operations/push_commands.py
command_reminder/operations/record_command.py
command_reminder/operations/remove_command.py
command_reminder/operations/common/__init__.py
command_reminder/operations/common/dict_viewer.py
command_reminder/operations/common/git.py
scripts/cr