Metadata-Version: 2.1
Name: command-reminder
Version: 1.1.0
Summary: Tool for saving/sharing your mostly used commands for fish shell
Home-page: https://github.com/faderskd/command-reminder
Author: faderskd
Author-email: daniel.faderski@gmail.com
License: MIT
Platform: UNKNOWN
Classifier: License :: OSI Approved :: MIT License
Classifier: Programming Language :: Python :: 3
Classifier: Programming Language :: Python :: 3.9
